HoloSTT/HoloSTT.py
HoloSTT/__init__.py
holostt-0.2.4.dist-info/METADATA
holostt-0.2.4.dist-info/WHEEL
holostt-0.2.4.dist-info/top_level.txt
holostt-0.2.4.dist-info/RECORD
