Metadata-Version: 2.4
Name: HoloSTT
Version: 0.2.4
Summary: Modern Speech Recognition with both active and ambient listening and keyboard 
Author: Tristan McBride Sr.
Author-email: "Tristan McBride Sr." <142635792+TristanMcBrideSr@users.noreply.github.com>
Maintainer-email: "Tristan McBride Sr." <142635792+TristanMcBrideSr@users.noreply.github.com>
License-Expression: Apache-2.0
Project-URL: Homepage, https://github.com/TristanMcBrideSr
Keywords: AI,Agents,Speech Recognition,Productivity,Automation
Classifier: Programming Language :: Python :: 3
Classifier: Operating System :: OS Independent
Classifier: Intended Audience :: Developers
Requires-Python: >=3.10
Requires-Dist: SpeechRecognition
Requires-Dist: requests
Requires-Dist: faster-whisper
Requires-Dist: torch
Requires-Dist: pyaudio
Requires-Dist: numpy
Dynamic: author
